{
	"backtrace" : 0,
	"backtraceGraph" : 
	{
		"commands" : [],
		"files" : 
		[
			"CMakeLists.txt"
		],
		"nodes" : 
		[
			{
				"file" : 0
			}
		]
	},
	"id" : "ZERO_CHECK::@6890427a1f51a3e7e1df",
	"isGeneratorProvided" : true,
	"name" : "ZERO_CHECK",
	"paths" : 
	{
		"build" : ".",
		"source" : "."
	},
	"sourceGroups" : 
	[
		{
			"name" : "CMake Rules",
			"sourceIndexes" : 
			[
				0
			]
		}
	],
	"sources" : 
	[
		{
			"backtrace" : 0,
			"isGenerated" : true,
			"path" : "C:/Users/Ryder/2023_20466053/Worksheet_6/build-Worksheet6_Exercise1_Qt-Desktop_Qt_6_6_2_MSVC2019_64bit-Debug/CMakeFiles/99613e337f1307791f70e9eeca8020e9/generate.stamp.rule",
			"sourceGroupIndex" : 0
		}
	],
	"type" : "UTILITY"
}
